hex_device/__init__.py
hex_device/arm.py
hex_device/arm_config.py
hex_device/chassis.py
hex_device/common_utils.py
hex_device/device_base.py
hex_device/device_base_optional.py
hex_device/device_factory.py
hex_device/error_type.py
hex_device/gamepad.py
hex_device/hands.py
hex_device/hex_device_api.py
hex_device/hex_socket.py
hex_device/imu.py
hex_device/kcp_client_core.py
hex_device/linear_lift.py
hex_device/motor_base.py
hex_device/sdt_hello.py
hex_device/zeta_lift.py
hex_device/generated/__init__.py
hex_device/generated/public_api_down_pb2.py
hex_device/generated/public_api_types_pb2.py
hex_device/generated/public_api_up_pb2.py
hex_device/generated/version.py
hex_device-1.3.15.dist-info/licenses/LICENSE.txt
hex_device-1.3.15.dist-info/METADATA
hex_device-1.3.15.dist-info/WHEEL
hex_device-1.3.15.dist-info/top_level.txt
hex_device-1.3.15.dist-info/RECORD
