Metadata-Version: 2.4
Name: hex_device
Version: 1.3.15
Summary: A Python library for controlling HexDevice robots and devices
Author-email: Jecjune <zejun.chen@hexfellow.com>
Maintainer-email: Jecjune <zejun.chen@hexfellow.com>
License-Expression: Apache-2.0
Project-URL: Homepage, https://github.com/hexfellow/hex_device_python
Project-URL: Repository, https://github.com/hexfellow/hex_device_python.git
Project-URL: Documentation, https://github.com/hexfellow/hex_device_python/wiki
Project-URL: Bug Reports, https://github.com/hexfellow/hex_device_python/issues
Keywords: robotics,hexfellow,device-control,protobuf,websocket
Classifier: Development Status :: 5 - Production/Stable
Classifier: Intended Audience :: Developers
Classifier: Intended Audience :: Science/Research
Classifier: Operating System :: OS Independent
Classifier: Programming Language :: Python :: 3
Classifier: Programming Language :: Python :: 3.9
Classifier: Programming Language :: Python :: 3.10
Classifier: Programming Language :: Python :: 3.11
Classifier: Programming Language :: Python :: 3.12
Classifier: Topic :: Scientific/Engineering :: Artificial Intelligence
Classifier: Topic :: Software Development :: Libraries :: Python Modules
Classifier: Topic :: System :: Hardware :: Hardware Drivers
Requires-Python: >=3.9
License-File: LICENSE.txt
Requires-Dist: numpy>=1.17.4
Requires-Dist: protobuf<6.0.0,>=5.29.4
Requires-Dist: websockets>=13.1
Requires-Dist: kcp==0.1.6
Dynamic: license-file
